pagebot/__init__.py
pagebot/constants.py
pagebot/document.py
pagebot/errors.py
pagebot/filepaths.py
pagebot/gradient.py
pagebot/publication.py
pagebot/style.py
pagebot/stylelib.py
pagebot/base/__init__.py
pagebot/base/article.py
pagebot/base/composer.py
pagebot/base/typesetter.py
pagebot/conditions/__init__.py
pagebot/conditions/align.py
pagebot/conditions/columns.py
pagebot/conditions/condition.py
pagebot/conditions/floating.py
pagebot/conditions/flow.py
pagebot/conditions/score.py
pagebot/conditions/text.py
pagebot/contexts/__init__.py
pagebot/contexts/basecontext/__init__.py
pagebot/contexts/basecontext/abstractcontext.py
pagebot/contexts/basecontext/babelrun.py
pagebot/contexts/basecontext/babelstring.py
pagebot/contexts/basecontext/basebeziercontour.py
pagebot/contexts/basecontext/basebezierpath.py
pagebot/contexts/basecontext/basebezierpoint.py
pagebot/contexts/basecontext/basebeziersegment.py
pagebot/contexts/basecontext/basebuilder.py
pagebot/contexts/basecontext/basecontext.py
pagebot/contexts/basecontext/baseimageobject.py
pagebot/contexts/basecontext/beziercontour.py
pagebot/contexts/basecontext/bezierpath.py
pagebot/contexts/flatcontext/__init__.py
pagebot/contexts/flatcontext/flatbabeldata.py
pagebot/contexts/flatcontext/flatbezierpath.py
pagebot/contexts/flatcontext/flatbuilder.py
pagebot/contexts/flatcontext/flatcontext.py
pagebot/contexts/flatcontext/flatrundata.py
pagebot/contexts/htmlcontext/__init__.py
pagebot/contexts/htmlcontext/htmlbuilder.py
pagebot/contexts/htmlcontext/htmlcontext.py
pagebot/contexts/htmlcontext/sitebuilder.py
pagebot/contexts/htmlcontext/xmlbuilder.py
pagebot/contexts/svgcontext/__init__.py
pagebot/contexts/svgcontext/svgbezierpath.py
pagebot/contexts/svgcontext/svgbuilder.py
pagebot/contexts/svgcontext/svgcontext.py
pagebot/contributions/__init__.py
pagebot/contributions/adobe/__init__.py
pagebot/contributions/adobe/kerndump/LICENSE.md
pagebot/contributions/adobe/kerndump/README.md
pagebot-1.0.3.dist-info/LICENSE.md
pagebot-1.0.3.dist-info/METADATA
pagebot-1.0.3.dist-info/WHEEL
pagebot-1.0.3.dist-info/top_level.txt
pagebot-1.0.3.dist-info/RECORD
