Metadata-Version: 2.1
Name: pagebot
Version: 1.0.3
Summary: Scripted page layout framework for Python.
Home-page: https://github.com/PageBot/PageBot
Author: Petr van Blokland, Michiel Kauw-A-Tjoe, Felipe Sanches, Dave Crossland
Author-email: r@petr.com
License: MIT
Platform: UNKNOWN
Classifier: Development Status :: 3 - Alpha
Classifier: Intended Audience :: Developers
Classifier: Intended Audience :: Other Audience
Classifier: License :: OSI Approved :: MIT License
Classifier: Operating System :: OS Independent
Classifier: Programming Language :: Python :: 3.6
Classifier: Programming Language :: Python :: Implementation :: PyPy
Classifier: Topic :: Artistic Software
Classifier: Topic :: Multimedia :: Graphics
Classifier: Topic :: Multimedia :: Graphics :: Editors
Classifier: Topic :: Multimedia :: Graphics :: Editors :: Raster-Based
Classifier: Topic :: Multimedia :: Graphics :: Editors :: Vector-Based
Classifier: Topic :: Multimedia :: Graphics :: Graphics Conversion
Classifier: Topic :: Multimedia :: Graphics :: Viewers
Classifier: Topic :: Scientific/Engineering :: Visualization
Classifier: Topic :: Software Development :: Libraries
Classifier: Topic :: Software Development :: Libraries :: Python Modules
Classifier: Topic :: Text Processing
Classifier: Topic :: Text Processing :: Fonts
Requires-Dist: booleanOperations
Requires-Dist: fontTools
Requires-Dist: libsass
Requires-Dist: markdown
Requires-Dist: Pillow
Requires-Dist: svgwrite
Requires-Dist: tornado
